jionlp/__init__.py
jionlp/algorithm/__init__.py
jionlp/algorithm/bpe/__init__.py
jionlp/algorithm/bpe/encoder_decoder.py
jionlp/algorithm/cws/__init__.py
jionlp/algorithm/cws/cws_data_converter.py
jionlp/algorithm/cws/cws_data_correction.py
jionlp/algorithm/cws/measure.py
jionlp/algorithm/keyphrase/__init__.py
jionlp/algorithm/keyphrase/extract_keyphrase.py
jionlp/algorithm/keyphrase/extract_keyphrase_bak.py
jionlp/algorithm/keyphrase/pos_combine_weights.json
jionlp/algorithm/mellm/__init__.py
jionlp/algorithm/mellm/llm_api.py
jionlp/algorithm/mellm/mellm.py
jionlp/algorithm/ner/__init__.py
jionlp/algorithm/ner/analyse_dataset.py
jionlp/algorithm/ner/check_person_name.py
jionlp/algorithm/ner/lexicon_ner.py
jionlp/algorithm/ner/measure.py
jionlp/algorithm/ner/money_extractor.py
jionlp/algorithm/ner/ner_accelerate.py
jionlp/algorithm/ner/ner_data_converter.py
jionlp/algorithm/ner/ner_entity_compare.py
jionlp/algorithm/ner/time_extractor.py
jionlp/algorithm/new_word/__init__.py
jionlp/algorithm/new_word/new_word_discovery.py
jionlp/algorithm/pos/__init__.py
jionlp/algorithm/pos/pos_data_converter.py
jionlp/algorithm/pos/pos_data_correction.py
jionlp/algorithm/sentiment/__init__.py
jionlp/algorithm/sentiment/sentiment_analysis.py
jionlp/algorithm/simhash/__init__.py
jionlp/algorithm/simhash/api.py
jionlp/algorithm/simhash/simhash.py
jionlp/algorithm/simhash/simhash_redis.py
jionlp/algorithm/summary/__init__.py
jionlp/algorithm/summary/extract_summary.py
jionlp/algorithm/summary/extract_summary_bak.py
jionlp/algorithm/text_classification/__init__.py
jionlp/algorithm/text_classification/analyse_dataset.py
jionlp/algorithm/text_classification/analyse_freq_words.py
jionlp/dictionary/TODO.txt
jionlp/dictionary/__init__.py
jionlp/dictionary/advertisement.txt
jionlp/dictionary/char_distribution.zip
jionlp/dictionary/china_location.zip
jionlp/dictionary/china_location_change.txt
jionlp/dictionary/chinese_char_dictionary.zip
jionlp/dictionary/chinese_idiom.zip
jionlp-1.5.26.dist-info/LICENSE
jionlp-1.5.26.dist-info/METADATA
jionlp-1.5.26.dist-info/WHEEL
jionlp-1.5.26.dist-info/entry_points.txt
jionlp-1.5.26.dist-info/top_level.txt
jionlp-1.5.26.dist-info/RECORD
