Metadata-Version: 2.1
Name: jionlp
Version: 1.5.26
Summary: Chinese NLP Preprocessing & Parsing
Home-page: https://github.com/dongrixinyu/JioNLP
Author: dongrixinyu
Author-email: dongrixinyu.89@163.com
License: Apache License 2.0
License-File: LICENSE
Requires-Dist: numpy
Requires-Dist: jiojio
Requires-Dist: requests
Requires-Dist: zipfile36
